curl/__init__.py
curl/curl-stub.py
curl/stub.py
wget/__init__.py
wget/stub.py
wget/wget-stub.py
aria2stub-0.9.1.dist-info/LICENSE
aria2stub-0.9.1.dist-info/METADATA
aria2stub-0.9.1.dist-info/WHEEL
aria2stub-0.9.1.dist-info/entry_points.txt
aria2stub-0.9.1.dist-info/top_level.txt
aria2stub-0.9.1.dist-info/RECORD
