Metadata-Version: 2.1
Name: aria2stub
Version: 0.9.1
Summary: Use aria2c instead for wget or curl to download large files using Debian alternatives subsystem instead of changing the shell scripts.
Home-page: https://github.com/SaiHarshaK/aria2c-for-wget-curl
Author: Sai Harsha Kottapalli
Author-email: k.saiharsha7@gmail.com
License: UNKNOWN
Platform: UNKNOWN
Classifier: Programming Language :: Python :: 3
Classifier: License :: OSI Approved :: MIT License
Requires-Python: >=3.6
